test/__init__.py
test/test.py
yangyaya-1.0.dist-info/METADATA
yangyaya-1.0.dist-info/RECORD
yangyaya-1.0.dist-info/WHEEL
yangyaya-1.0.dist-info/top_level.txt
