Metadata-Version: 2.1
Name: yangyaya
Version: 1.0
Summary: An feature extraction algorithm
Home-page: https://github.com/zhanghang-z
Author: LiangjunFeng
Author-email: zhumavip@163.com
License: UNKNOWN
Keywords: pip,yangyuya-test,featureextraction
Platform: any
Requires-Dist: numpy
